AUTHORS.rst
CONTRIBUTING.rst
HISTORY.rst
LICENSE
MANIFEST.in
README.rst
requirements.txt
requirements_dev.txt
setup.cfg
setup.py
docs/Makefile
docs/authors.rst
docs/conf.py
docs/contributing.rst
docs/history.rst
docs/index.rst
docs/installation.rst
docs/make.bat
docs/modules.rst
docs/readme.rst
docs/smokesignal.rst
docs/usage.rst
docs/_build/html/_static/ajax-loader.gif
docs/_build/html/_static/comment-bright.png
docs/_build/html/_static/comment-close.png
docs/_build/html/_static/comment.png
docs/_build/html/_static/down-pressed.png
docs/_build/html/_static/down.png
docs/_build/html/_static/file.png
docs/_build/html/_static/minus.png
docs/_build/html/_static/plus.png
docs/_build/html/_static/up-pressed.png
docs/_build/html/_static/up.png
smokesignal/__init__.py
smokesignal/client.py
smokesignal/errors.py
smokesignal/service.py
smokesignal_etcd.egg-info/PKG-INFO
smokesignal_etcd.egg-info/SOURCES.txt
smokesignal_etcd.egg-info/dependency_links.txt
smokesignal_etcd.egg-info/not-zip-safe
smokesignal_etcd.egg-info/requires.txt
smokesignal_etcd.egg-info/top_level.txt
tests/__init__.py
tests/test_smokesignal.py