Metadata-Version: 1.1
Name: smokesignal-etcd
Version: 0.3.3
Summary: Simple library to publish and read service descriptions using etcd
Home-page: https://github.com/tmacro/smokesignal
Author: Taylor McKinnon
Author-email: taylor@uncannypacket.com
License: MIT license
Keywords: smokesignal
Platform: UNKNOWN
Classifier: Development Status :: 2 - Pre-Alpha
Classifier: Intended Audience :: Developers
Classifier: License :: OSI Approved :: MIT License
Classifier: Natural Language :: English
Classifier: Programming Language :: Python :: 2
Classifier: Programming Language :: Python :: 2.7
Classifier: Programming Language :: Python :: 3
Classifier: Programming Language :: Python :: 3.5
